objective_rating_metrics/__init__.py
objective_rating_metrics/rating.py
objective_rating_metrics-1.3.dist-info/LICENSE
objective_rating_metrics-1.3.dist-info/METADATA
objective_rating_metrics-1.3.dist-info/WHEEL
objective_rating_metrics-1.3.dist-info/top_level.txt
objective_rating_metrics-1.3.dist-info/RECORD
