Metadata-Version: 2.1
Name: objective_rating_metrics
Version: 1.3
Summary: Python implementation of ISO/TS 18571
Home-page: https://openvt.eu/validation-metrics/ISO18571
Author: VSI TU Graz
Author-email: vsi.office@tugraz.at
Requires-Python: >=3.8
License-File: LICENSE
Requires-Dist: pyyaml
Requires-Dist: pillow
Requires-Dist: jsonschema
Requires-Dist: ordered-set
Requires-Dist: certifi
Requires-Dist: shapely
Requires-Dist: numpy
Requires-Dist: pandas
Requires-Dist: dtwalign
